llama_index/packs/agents_llm_compiler/__init__.py
llama_index/packs/agents_llm_compiler/base.py
llama_index/packs/agents_llm_compiler/output_parser.py
llama_index/packs/agents_llm_compiler/prompts.py
llama_index/packs/agents_llm_compiler/schema.py
llama_index/packs/agents_llm_compiler/step.py
llama_index/packs/agents_llm_compiler/task_fetching_unit.py
llama_index/packs/agents_llm_compiler/utils.py
llama_index_packs_agents_llm_compiler-0.3.1.dist-info/METADATA
llama_index_packs_agents_llm_compiler-0.3.1.dist-info/WHEEL
llama_index_packs_agents_llm_compiler-0.3.1.dist-info/licenses/LICENSE
llama_index_packs_agents_llm_compiler-0.3.1.dist-info/RECORD
