Metadata-Version: 2.4
Name: llama-index-packs-agents-llm-compiler
Version: 0.3.1
Summary: llama-index packs agents llm compiler
Author-email: Your Name <you@example.com>
Maintainer: jerryjliu
License-Expression: MIT
License-File: LICENSE
Keywords: agent,compiler,llm
Requires-Python: <4.0,>=3.9
Requires-Dist: llama-index-core<0.13,>=0.12.0
Requires-Dist: llama-index-llms-openai<0.5,>=0.4.0
